aes_pipe/__init__.py
aes_pipe/__main__.py
aes_pipe-1.0.3.dist-info/METADATA
aes_pipe-1.0.3.dist-info/RECORD
aes_pipe-1.0.3.dist-info/WHEEL
aes_pipe-1.0.3.dist-info/entry_points.txt
aes_pipe-1.0.3.dist-info/top_level.txt
