Metadata-Version: 2.1
Name: aes-pipe
Version: 1.0.3
Summary: Encrypting piped data with AES
Home-page: https://github.com/2sh/aes-pipe
Author: Seán Hewitt
Author-email: contact@2sh.me
License: UNKNOWN
Platform: UNKNOWN
Classifier: Programming Language :: Python :: 3
Classifier: License :: OSI Approved :: GNU General Public License v3 or later (GPLv3+)
Classifier: Operating System :: OS Independent
Classifier: Topic :: Security :: Cryptography
Requires-Python: >=3.4
Requires-Dist: pycrypto
